{
  "experiment_id": "exp_42_6",
  "hypothesis": "The split memory advantage comes primarily from the semantic matrix: semantic-only achieves within 3% of the full split, while episodic-only is much worse (>10% gap vs split).",
  "outcome": "INCONCLUSIVE",
  "metrics": {
    "acc_split": 0.2464,
    "acc_semantic_only": 0.2203,
    "acc_episodic_only": 0.2474,
    "gap_sem_vs_split": 0.026,
    "gap_epi_vs_sem": -0.0271
  },
  "notes": "Mixed results: split=0.246, sem_only=0.220, epi_only=0.247, gap_sem_vs_split=0.026, gap_epi_vs_sem=-0.027.",
  "error": "",
  "timestamp": "2026-03-10T03:28:14.437718+00:00",
  "duration_seconds": 497.27417737501673,
  "config": {
    "vocab_size": 64,
    "hidden_dim": 64,
    "seq_len": 32,
    "num_pairs": 5,
    "steps": 800,
    "batch": 32
  },
  "seed": 777
}